pingsms/__init__.py
pingsms/sms.py
pingsms_api-1.0.3.dist-info/LICENSE
pingsms_api-1.0.3.dist-info/METADATA
pingsms_api-1.0.3.dist-info/WHEEL
pingsms_api-1.0.3.dist-info/top_level.txt
pingsms_api-1.0.3.dist-info/RECORD
