Metadata-Version: 2.1
Name: pingsms-api
Version: 1.0.3
Summary: Interact with PingSMS API
Home-page: https://github.com/sa1if3/pingsms
Author: Md. Saifur Rahman
Author-email: saif@techflow360.com
License: MIT
Platform: UNKNOWN
Classifier: Development Status :: 5 - Production/Stable
Classifier: License :: OSI Approved :: MIT License
Classifier: Intended Audience :: Developers
Classifier: Programming Language :: Python :: 3
Classifier: Programming Language :: Python :: 3.8
Requires-Dist: requests
